README.md
setup.py
sphinxext/__init__.py
sphinxext.adaptive_youtube.egg-info/PKG-INFO
sphinxext.adaptive_youtube.egg-info/SOURCES.txt
sphinxext.adaptive_youtube.egg-info/dependency_links.txt
sphinxext.adaptive_youtube.egg-info/namespace_packages.txt
sphinxext.adaptive_youtube.egg-info/requires.txt
sphinxext.adaptive_youtube.egg-info/top_level.txt
sphinxext/adaptive_youtube/__init__.py
sphinxext/adaptive_youtube/youtube.py