Metadata-Version: 1.1
Name: sphinxext.adaptive-youtube
Version: 0.0.2
Summary: embedding gist to sphinx
Home-page: https://github.com/john-sane/adaptive-youtube
Author: @john_sane
Author-email: UNKNOWN
License: LGPLv3
Platform: UNKNOWN
Classifier: Programming Language :: Python
Classifier: Development Status :: 4 - Beta
Classifier: License :: OSI Approved :: GNU Lesser General Public License v3 (LGPLv3)
Classifier: Programming Language :: Python :: 3
Classifier: Programming Language :: Python :: 3.3
Classifier: Programming Language :: Python :: 3.7
Classifier: Topic :: Software Development :: Documentation
